exhaufs-0.94.data/scripts/exhaufs
src/__init__.py
src/build_classifiers.py
src/build_regressors.py
src/make_classifier_summary.py
src/make_km_plot_for_classifier.py
src/make_regressor_summary.py
src/running_time_estimator.py
src/core/__init__.py
src/core/accuracy_scores.py
src/core/feature_pre_selectors.py
src/core/feature_selectors.py
src/core/preprocessors.py
src/core/utils.py
src/core/base/__init__.py
src/core/base/base.py
src/core/base/feature_pre_selector.py
src/core/base/feature_selector.py
src/core/base/model.py
src/core/base/preprocessor.py
src/core/classification/__init__.py
src/core/classification/accuracy_scores.py
src/core/classification/classification.py
src/core/classification/classifiers.py
src/core/classification/feature_selectors.py
src/core/regression/__init__.py
src/core/regression/regression.py
src/core/regression/regressors.py
src/core/regression/utils.py
src/core/regression/accuracy_scores/__init__.py
src/core/regression/accuracy_scores/concordance.py
src/core/regression/accuracy_scores/dynamic_auc.py
src/core/regression/accuracy_scores/hazard_ratio.py
src/core/regression/accuracy_scores/logrank_test.py
src/core/regression/feature_selectors/__init__.py
src/core/regression/feature_selectors/cox/__init__.py
src/core/regression/feature_selectors/cox/concordance.py
src/core/regression/feature_selectors/cox/dynamic_auc.py
src/core/regression/feature_selectors/cox/hazard_ratio.py
src/core/regression/feature_selectors/cox/l1_cox.py
src/core/regression/feature_selectors/cox/likelihood.py
src/core/regression/feature_selectors/cox/logrank.py
src/core/regression/models/__init__.py
src/core/regression/models/cox.py
src/core/wrappers/__init__.py
src/core/wrappers/features_selectors.py
src/utils/__init__.py
src/utils/common.py
src/utils/summary_regressors.py
test/__init__.py
test/feature_selectors.py
exhaufs-0.94.dist-info/LICENSE
exhaufs-0.94.dist-info/METADATA
exhaufs-0.94.dist-info/WHEEL
exhaufs-0.94.dist-info/top_level.txt
exhaufs-0.94.dist-info/RECORD
