Metadata-Version: 2.1
Name: exhaufs
Version: 0.94
Summary: Exhaustive Feature Selection
Home-page: https://github.com/s-a-nersisyan/ExhauFS
Author: HSE.Bioinformatics
Author-email: s.a.nersisyan@gmail.com
License: UNKNOWN
Platform: UNKNOWN
Classifier: Programming Language :: Python :: 3
Classifier: License :: OSI Approved :: MIT License
Classifier: Operating System :: POSIX :: Linux
Classifier: Operating System :: Microsoft :: Windows
Classifier: Operating System :: MacOS
Requires-Dist: scipy
Requires-Dist: scikit-learn
Requires-Dist: numpy
Requires-Dist: pandas
Requires-Dist: lifelines
Requires-Dist: scikit-survival
